{"category":16,"category2":1,"currencyrewards":[],"icon":"quest-start","id":14471,"itemchoices":[[53422,1],[53430,1],[53437,1]],"itemrewards":[],"level":13,"money":0,"name":"First Degree Mortar","reprewards":[[1133,250]],"reqclass":0,"reqlevel":10,"side":2,"titlereward":0,"type":0,"xp":910,"popularity":46,"tooltip":"<table><tr><td><b class=\"q\">First Degree Mortar</b></td></tr></table><table><tr><td><br />Use a Goblin Mortar to slaughter 60 Spitelash Attackers<br /><br /><span class=\"q\">Requirements:</span><br /> - Spitelash Attackers blown to bits x 60</td></tr></table>"}