{"category":85,"category2":0,"currencyrewards":[],"icon":"quest-start","id":25029,"itemchoices":[[3446,1],[3440,1]],"itemrewards":[],"level":9,"money":300,"name":"Deaths in the Family","reprewards":[[68,250]],"reqclass":0,"reqlevel":6,"side":2,"titlereward":0,"type":0,"xp":780,"popularity":13,"tooltip":"<table><tr><td><b class=\"q\">Deaths in the Family</b></td></tr></table><table><tr><td><br />Obtain Gregor's Remains, Nissa's Remains, Thurman's Remains, and Devlin's Remains.<br /><br /><span class=\"q\">Requirements:</span><br /> - Nissa's Remains<br /> - Gregor's Remains<br /> - Thurman's Remains<br /> - Devlin's Remains</td></tr></table>"}