{"category":3430,"category2":0,"currencyrewards":[],"icon":"quest-start","id":8346,"itemchoices":[[20999,1],[21000,1],[21001,1]],"itemrewards":[],"level":3,"money":0,"name":"Thirst Unending","reprewards":[[911,250]],"reqclass":0,"reqlevel":2,"side":2,"titlereward":0,"type":0,"xp":250,"popularity":13,"tooltip":"<table><tr><td><b class=\"q\">Thirst Unending</b></td></tr></table><table><tr><td><br />Use your Arcane Torrent racial ability on a Mana Wyrm, then return to Arcanist Helion.<br /><br /><span class=\"q\">Requirements:</span><br /> - Mana Tap creature</td></tr></table>"}