{"category":3430,"category2":0,"currencyrewards":[],"icon":"quest-start","id":8885,"itemchoices":[[23398,1],[23395,1],[23397,1],[23396,1]],"itemrewards":[],"level":9,"money":600,"name":"The Ring of Mmmrrrggglll","reprewards":[[911,350]],"reqclass":0,"reqlevel":5,"side":2,"titlereward":0,"type":0,"xp":980,"popularity":12,"tooltip":"<table><tr><td><b class=\"q\">The Ring of Mmmrrrggglll</b></td></tr></table><table><tr><td><br />Retrieve the Ring of Mmmrrrggglll from the Grimscale chieftain's dead clutches. &nbsp;Return it to Hathvelion Sungaze in the Eversong Woods on the bluff overlooking the Tranquil Shore.<br /><br /><span class=\"q\">Requirements:</span><br /> - Ring of Mmmrrrggglll</td></tr></table>"}