{"category":3524,"category2":1,"currencyrewards":[],"icon":"quest-start","id":9311,"itemchoices":[[23390,1],[23391,1],[23392,1],[23393,1],[24441,1],[25553,1]],"itemrewards":[],"level":5,"money":300,"name":"Blood Elf Spy","reprewards":[[930,500]],"reqclass":0,"reqlevel":2,"side":1,"titlereward":0,"type":0,"xp":670,"popularity":60,"tooltip":"<table><tr><td><b class=\"q\">Blood Elf Spy</b></td></tr></table><table><tr><td><br />Slay Surveyor Candress and then inform Vindicator Aldar at the Crash Site in Ammen Vale.<br /><br /><span class=\"q\">Requirements:</span><br /> - Surveyor Candress</td></tr></table>"}