{
	"id": 15306,
	"name": "Feral Bindings",
	"icon": "inv_bracer_05",
	"popularity": 16,
	"armor": 32,
	"class": "ARMOR",
	"quality": "UNCOMMON",
	"subclass": "LEATHER",
	"type": "WRISTS",
	"rand": {
		"of the Monkey": {
			"id": 587,
			"chance": 18,
			"stats": { "Agility": 2, "Stamina": 2 }
		},
		"of the Owl": {
			"id": 757,
			"chance": 12.4,
			"stats": { "Intellect": 2, "Spirit": 2 }
		},
		"of Agility": { "id": 18, "chance": 9.9, "stats": { "Agility": 3 } },
		"of the Eagle": {
			"id": 842,
			"chance": 9.6,
			"stats": { "Intellect": 2, "Stamina": 2 }
		},
		"of the Whale": {
			"id": 1012,
			"chance": 8.9,
			"stats": { "Spirit": 2, "Stamina": 2 }
		},
		"of Stamina": { "id": 22, "chance": 8.5, "stats": { "Stamina": 3 } },
		"of Intellect": { "id": 26, "chance": 8, "stats": { "Intellect": 3 } },
		"of Power": { "id": 1549, "chance": 6.4, "stats": { "Attack Power": 6 } },
		"of Spirit": { "id": 28, "chance": 6.1, "stats": { "Spirit": 3 } },
		"of the Wolf": {
			"id": 502,
			"chance": 4.5,
			"stats": { "Agility": 2, "Spirit": 2 }
		},
		"of the Falcon": {
			"id": 238,
			"chance": 4.1,
			"stats": { "Agility": 2, "Intellect": 2 }
		},
		"of Nature's Wrath": {
			"id": 1991,
			"chance": 1.7,
			"stats": { "Nature Spell Damage": 4 }
		},
		"of Arcane Wrath": {
			"id": 1801,
			"chance": 1.2,
			"stats": { "Arcane Spell Damage": 4 }
		},
		"of Healing": { "id": 2029, "chance": 0.7, "stats": { "Spell Power": 4 } }
	},
	"source": "DROP"
}
