{"id":"3434","cooldown":60000,"sellprice":3,"quality":1,"icon":"inv_misc_dust_02","screenshot":{},"attainable":0,"flags2":24576,"displayName":"","qualityTier":0,"tooltip":"<table><tr><td><!--nstart--><b class=\"q1\">Slumber Sand</b><!--nend--><!--ndstart--><!--ndend--><span class=\"q whtt-extra whtt-ilvl\"><br>Item Level <!--ilvl-->7</span><!--bo--><br>Binds when picked up<!--ue--><!--ebstats--><!--egstats--><!--eistats--><!--nameDescStats--></td></tr></table><table><tr><td><span class=\"q2\">Use: <a href=\"/cata/spell=700/sleep\" class=\"q2\">Puts the enemy target to sleep for up to 20 sec. &nbsp;Any damage caused will awaken the target. &nbsp;Only one target can be asleep at a time. Unreliable on targets above level 30.</a> (1 Min Cooldown)</span><div class=\"whtt-extra whtt-maxstack\">Max Stack: 10</div><div class=\"whtt-sellprice\">Sell Price: <span class=\"moneycopper\">3</span></div></td></tr></table>"}