{
	"id": 38785,
	"name": "Enchant Boots - Minor Stamina",
	"icon": "inv_misc_enchantedscroll",
	"itemLevel": 1,
	"popularity": 6,
	"class": "CONSUMABLE",
	"quality": "COMMON",
	"subclass": "ITEM_ENHANCEMENT",
	"stats": { "Stamina": 1 },
	"source": "CRAFT",
	"sourceId": 7863,
	"sourceName": "Enchanting",
	"sourceType": "SPELL",
	"spell": {
		"type": "Use",
		"id": 7863,
		"icon": "inv_enchant_formulagood_01",
		"name": "Enchant Boots - Minor Stamina",
		"text": "Permanently enchant boots to increase Stamina by 1."
	},
	"enchant": { "description": "+1 Stamina", "id": 66, "types": ["FEET"] }
}
