{
	"id": 38846,
	"name": "Enchant Bracer - Greater Strength",
	"icon": "inv_misc_enchantedscroll",
	"popularity": 3,
	"class": "CONSUMABLE",
	"quality": "COMMON",
	"subclass": "ITEM_ENHANCEMENT",
	"stats": { "Strength": 7 },
	"sourceId": 13939,
	"sourceName": "Enchant Bracer - Greater Strength",
	"sourceType": "SPELL",
	"spell": {
		"type": "Use",
		"id": 13939,
		"icon": "spell_holy_greaterheal",
		"name": "Enchant Bracer - Greater Strength",
		"text": "Permanently enchants bracers to give +7 Strength."
	},
	"enchant": { "description": "+7 Strength", "id": 927, "types": ["WRISTS"] }
}
