{
	"id": 58928,
	"bind": "Binds when picked up",
	"name": "House Wrynn Halberd",
	"icon": "inv_weapon_halberd_23",
	"requiredLevel": 12,
	"itemLevel": 15,
	"dmgMin": 29,
	"dmgMax": 54,
	"speed": 3,
	"dps": 13.83,
	"popularity": 18,
	"side": "ALLIANCE",
	"class": "WEAPON",
	"quality": "RARE",
	"subclass": "POLEARM",
	"type": "TWO_HAND",
	"stats": { "Hit Rating": 4, "Agility": 4, "Stamina": 4 },
	"source": "QUEST",
	"sourceId": 26322,
	"sourceName": "Rise of the Brotherhood",
	"sourceType": "QUEST"
}
